Metadata-Version: 2.1
Name: 3p0
Version: 0.0.9
Summary: A multi-language library for translating commands between PyTorch, TensorFlow, and TensorFlow.js
Home-page: https://github.com/openmined/threepio
Author: openmined
License: Apache License, Version 2.0
Platform: UNKNOWN
Requires-Python: >=3.6
